{
  "id": "4fac95f8-74cc-4083-8bb5-d355e4c9ec7c",
  "tenantid": "od",
  "code": "INBOX.InboxQueryConfiguration",
  "description": null,
  "definition": {
    "type": "object",
    "$schema": "http://json-schema.org/draft-07/schema#",
    "required": [
      "module"
    ],
    "x-unique": [
      "module"
    ],
    "properties": {
      "index": {
        "type": "string"
      },
      "module": {
        "type": "string"
      },
      "sortBy": {
        "type": [
          "object",
          "null"
        ]
      },
      "sourceFilterPathList": {
        "type": "array",
        "items": {
          "type": "string"
        }
      },
      "allowedSearchCriteria": {
        "type": "array",
        "items": {
          "type": [
            "object",
            "null"
          ]
        }
      }
    }
  },
  "isactive": true,
  "createdby": "71d23f7e-30c9-4ba4-b81b-e1862cd3fd9d",
  "lastmodifiedby": "71d23f7e-30c9-4ba4-b81b-e1862cd3fd9d",
  "createdtime": 1729162689553,
  "lastmodifiedtime": 1729162689553
}